Workbook
Name \0: #REF!
Name \A: #REF!
Name \APR: #REF!
Name \AUG: #REF!
Name \B: #REF!
Name \C: #N/A
Name \DEC: #REF!
Name \F: #REF!
Name \FEB: #REF!
Name \H: #REF!
Name \I: #REF!
Name \JAN: #REF!
Name \JUL: #REF!
Name \JUN: #REF!
Name \L: #REF!
Name \m: #REF!
Name \MAR: #REF!
Name \MAY: #REF!
Name \NOV: #REF!
Name \OCT: #REF!
Name \P: #REF!
Name \p1: #REF!
Name \Q: #REF!
Name \QTR1: #REF!
Name \QTR2: #REF!
Name \QTR3: #REF!
Name \QTR4: #REF!
Name \R: #REF!
Name \S: #REF!
Name \SEP: #REF!
Name \W: #REF!
Name \Z: #N/A
Name _.._Specification_name__Quikinc4: #REF!
Name ____________EMP2: #REF!
Name ____________VAL1: #REF!
Name ___________EMP2: #REF!
Name ___________VAL1: #REF!
Name __________EMP2: #REF!
Name __________VAL1: #REF!
Name _________Div2: #REF!
Name _________EMP2: #REF!
Name _________VAL1: #REF!
Name ________Div2: #REF!
Name ________EMP2: #REF!
Name ________VAL1: #REF!
Name _______EMP2: #REF!
Name _______VAL1: #REF!
Name ______Div2: #REF!
Name ______EMP2: #REF!
Name ______pg10: #REF!
Name ______Pg2: #REF!
Name ______Pg3: #REF!
Name ______Pg4: #REF!
Name ______Pg5: #REF!
Name ______Pg6: #REF!
Name ______Pg7: #REF!
Name ______Pg8: #REF!
Name ______Pg9: #REF!
Name ______VAL1: #REF!
Name _____Div2: #REF!

Sheet Output AVP
B2: Print? (Yes=1, No=0) | C2: 1
B5: ($ in millions) | C5: Metric | E5: =+F5-10 -> 120 | F5: =+G5-10 -> 130 | G5: =+H5-5 -> 140 | H5: =+I5-5 -> 145 | I5: 150 | J5: =+I5+5 -> 155 | K5: =+J5+5 -> 160 | L5: =+K5+5 -> 165 | M5: =+L5+5 -> 170 | Q5: =+B5 -> ($ in millions) | R5: Metric | T5: =G5 -> 140 | U5: =I5 -> 150 | V5: =K5 -> 160
B6: EV / 2023 Adj. EBITDA | C6: =+Model!$I$109 -> 4 | E6: =E$5/$C6 -> 30 | F6: =F$5/$C6 -> 32.5 | G6: =G$5/$C6 -> 35 | H6: =H$5/$C6 -> 36.25 | I6: =I$5/$C6 -> 37.5 | J6: =J$5/$C6 -> 38.75 | K6: =K$5/$C6 -> 40 | L6: =L$5/$C6 -> 41.25 | M6: =M$5/$C6 -> 42.5 | Q6: =B6 -> EV / 2023 Adj. EBITDA | R6: =C6 -> 4 | T6: =INDEX($E6:$M6,MATCH(T$5,$E$5:$M$5,0)) -> 35 | U6: =INDEX($G6:$M6,MATCH(U$5,$G$5:$M$5,0)) -> 37.5 | V6: =INDEX($G6:$M6,MATCH(V$5,$G$5:$M$5,0)) -> 40
B7: EV / '23 Adj. EBITDA - Capex | C7: =+Model!I128 -> 2 | E7: =E$5/$C7 -> 60 | F7: =F$5/$C7 -> 65 | G7: =G$5/$C7 -> 70 | H7: =H$5/$C7 -> 72.5 | I7: =I$5/$C7 -> 75 | J7: =J$5/$C7 -> 77.5 | K7: =K$5/$C7 -> 80 | L7: =L$5/$C7 -> 82.5 | M7: =M$5/$C7 -> 85 | Q7: =B7 -> EV / '23 Adj. EBITDA - Capex | R7: =C7 -> 2 | T7: =INDEX($E7:$M7,MATCH(T$5,$E$5:$M$5,0)) -> 70 | U7: =INDEX($G7:$M7,MATCH(U$5,$G$5:$M$5,0)) -> 75 | V7: =INDEX($G7:$M7,MATCH(V$5,$G$5:$M$5,0)) -> 80
B8: EV / '24E Adj. EBITDA | C8: =+Model!J109 -> 39.054 | E8: =E$5/$C8 -> 3.0726686 | F8: =F$5/$C8 -> 3.3287243 | G8: =G$5/$C8 -> 3.58478 | H8: =H$5/$C8 -> 3.7128079 | I8: =I$5/$C8 -> 3.8408358 | J8: =J$5/$C8 -> 3.9688636 | K8: =K$5/$C8 -> 4.0968915 | L8: =L$5/$C8 -> 4.2249193 | M8: =M$5/$C8 -> 4.3529472 | Q8: =B8 -> EV / '24E Adj. EBITDA | R8: =C8 -> 39.054 | T8: =INDEX($E8:$M8,MATCH(T$5,$E$5:$M$5,0)) -> 3.58478 | U8: =INDEX($G8:$M8,MATCH(U$5,$G$5:$M$5,0)) -> 3.8408358 | V8: =INDEX($G8:$M8,MATCH(V$5,$G$5:$M$5,0)) -> 4.0968915
B9: EV / '24E Adj. EBITDA - Capex | C9: =+Model!J128 -> 37.848 | E9: =E$5/$C9 -> 3.170577 | F9: =F$5/$C9 -> 3.4347918 | G9: =G$5/$C9 -> 3.6990066 | H9: =H$5/$C9 -> 3.8311139 | I9: =I$5/$C9 -> 3.9632213 | J9: =J$5/$C9 -> 4.0953287 | K9: =K$5/$C9 -> 4.2274361 | L9: =L$5/$C9 -> 4.3595434 | M9: =M$5/$C9 -> 4.4916508 | Q9: =B9 -> EV / '24E Adj. EBITDA - Capex | R9: =C9 -> 37.848 | T9: =INDEX($E9:$M9,MATCH(T$5,$E$5:$M$5,0)) -> 3.6990066 | U9: =INDEX($G9:$M9,MATCH(U$5,$G$5:$M$5,0)) -> 3.9632213 | V9: =INDEX($G9:$M9,MATCH(V$5,$G$5:$M$5,0)) -> 4.2274361
B10: EV / '25E Adj. EBITDA | C10: =+Model!K95 -> 39.31054 | E10: =E$5/$C10 -> 3.0526164 | F10: =F$5/$C10 -> 3.3070011 | G10: =G$5/$C10 -> 3.5613858 | H10: =H$5/$C10 -> 3.6885782 | I10: =I$5/$C10 -> 3.8157705 | J10: =J$5/$C10 -> 3.9429629 | K10: =K$5/$C10 -> 4.0701552 | L10: =L$5/$C10 -> 4.1973476 | M10: =M$5/$C10 -> 4.3245399 | Q10: =B10 -> EV / '25E Adj. EBITDA | R10: =C10 -> 39.31054 | T10: =INDEX($E10:$M10,MATCH(T$5,$E$5:$M$5,0)) -> 3.5613858 | U10: =INDEX($G10:$M10,MATCH(U$5,$G$5:$M$5,0)) -> 3.8157705 | V10: =INDEX($G10:$M10,MATCH(V$5,$G$5:$M$5,0)) -> 4.0701552
B11: EV / '25E Adj. EBITDA - Capex | C11: =+Model!K128 -> 38.09848 | E11: =E$5/$C11 -> 3.149732 | F11: =F$5/$C11 -> 3.4122096 | G11: =G$5/$C11 -> 3.6746873 | H11: =H$5/$C11 -> 3.8059261 | I11: =I$5/$C11 -> 3.9371649 | J11: =J$5/$C11 -> 4.0684038 | K11: =K$5/$C11 -> 4.1996426 | L11: =L$5/$C11 -> 4.3308814 | M11: =M$5/$C11 -> 4.4621203 | Q11: =B11 -> EV / '25E Adj. EBITDA - Capex | R11: =C11 -> 38.09848 | T11: =INDEX($E11:$M11,MATCH(T$5,$E$5:$M$5,0)) -> 3.6746873 | U11: =INDEX($G11:$M11,MATCH(U$5,$G$5:$M$5,0)) -> 3.9371649 | V11: =INDEX($G11:$M11,MATCH(V$5,$G$5:$M$5,0)) -> 4.1996426
B13: EV / NTAV (Dec. '23) | C13: =+Model!I336 -> 0 | E13: =E$5/$C13 -> #DIV/0! | F13: =F$5/$C13 -> #DIV/0! | G13: =G$5/$C13 -> #DIV/0! | H13: =H$5/$C13 -> #DIV/0! | I13: =I$5/$C13 -> #DIV/0! | J13: =J$5/$C13 -> #DIV/0! | K13: =K$5/$C13 -> #DIV/0! | L13: =L$5/$C13 -> #DIV/0! | M13: =M$5/$C13 -> #DIV/0! | Q13: =B13 -> EV / NTAV (Dec. '23) | R13: =C13 -> 0 | T13: =INDEX($E13:$M13,MATCH(T$5,$E$5:$M$5,0)) -> #DIV/0! | U13: =INDEX($G13:$M13,MATCH(U$5,$G$5:$M$5,0)) -> #DIV/0! | V13: =INDEX($G13:$M13,MATCH(V$5,$G$5:$M$5,0)) -> #DIV/0!
B14: EV / NWC (Dec. '23) | C14: =+Model!I335 -> 0 | E14: =E$5/$C14 -> #DIV/0! | F14: =F$5/$C14 -> #DIV/0! | G14: =G$5/$C14 -> #DIV/0! | H14: =H$5/$C14 -> #DIV/0! | I14: =I$5/$C14 -> #DIV/0! | J14: =J$5/$C14 -> #DIV/0! | K14: =K$5/$C14 -> #DIV/0! | L14: =L$5/$C14 -> #DIV/0! | M14: =M$5/$C14 -> #DIV/0! | Q14: =B14 -> EV / NWC (Dec. '23) | R14: =C14 -> 0 | T14: =INDEX($E14:$M14,MATCH(T$5,$E$5:$M$5,0)) -> #DIV/0! | U14: =INDEX($G14:$M14,MATCH(U$5,$G$5:$M$5,0)) -> #DIV/0! | V14: =INDEX($G14:$M14,MATCH(V$5,$G$5:$M$5,0)) -> #DIV/0!
B16: Debt / EBITDA | I16: =+Model!C10/Model!I95 -> -15 | Q16: =B16 -> Debt / EBITDA
C18: Returns | H18: =+Model!O378 -> 2.6873373 | I18: =+Model!O380 -> 0.25837345
J20: weight
C21: Base | J21: 0.5
C22: Upside | J22: 0.3
C23: Downturn | J23: 0.2
C24: Wtd. Avg. | H24: =SUMPRODUCT(H21:H23,$J21:$J23) -> 0 | I24: =SUMPRODUCT(I21:I23,$J21:$J23) -> 0
AB35: Sum of the Parts
AB37: =Model!H24 -> 45657 | AC37: =EOMONTH(AB37,12) -> 46022 | AD37: =#REF! -> #REF! | AE37: =Model!J24 -> 46387 | AF37: =EOMONTH(AE37,12) -> 46752
Z38: Revenues
Z39: =#REF! -> #REF! | AB39: =_xlfn.XLOOKUP(AB$37,#REF!,#REF!) -> #REF! | AC39: =_xlfn.XLOOKUP(AC$37,#REF!,#REF!) -> #REF! | AD39: =_xlfn.XLOOKUP(AD$37,#REF!,#REF!) -> #REF! | AE39: =_xlfn.XLOOKUP(AE$37,#REF!,#REF!) -> #REF! | AF39: =_xlfn.XLOOKUP(AF$37,#REF!,#REF!) -> #REF!
Z40: =#REF! -> #REF! | AB40: =_xlfn.XLOOKUP(AB$37,#REF!,#REF!) -> #REF! | AC40: =_xlfn.XLOOKUP(AC$37,#REF!,#REF!) -> #REF! | AD40: =_xlfn.XLOOKUP(AD$37,#REF!,#REF!) -> #REF! | AE40: =_xlfn.XLOOKUP(AE$37,#REF!,#REF!) -> #REF! | AF40: =_xlfn.XLOOKUP(AF$37,#REF!,#REF!) -> #REF!
Z41: =#REF! -> #REF! | AB41: =_xlfn.XLOOKUP(AB$37,#REF!,#REF!) -> #REF! | AC41: =_xlfn.XLOOKUP(AC$37,#REF!,#REF!) -> #REF! | AD41: =_xlfn.XLOOKUP(AD$37,#REF!,#REF!) -> #REF! | AE41: =_xlfn.XLOOKUP(AE$37,#REF!,#REF!) -> #REF! | AF41: =_xlfn.XLOOKUP(AF$37,#REF!,#REF!) -> #REF!
Z42: =#REF! -> #REF! | AB42: =_xlfn.XLOOKUP(AB$37,#REF!,#REF!) -> #REF! | AC42: =_xlfn.XLOOKUP(AC$37,#REF!,#REF!) -> #REF! | AD42: =_xlfn.XLOOKUP(AD$37,#REF!,#REF!) -> #REF! | AE42: =_xlfn.XLOOKUP(AE$37,#REF!,#REF!) -> #REF! | AF42: =_xlfn.XLOOKUP(AF$37,#REF!,#REF!) -> #REF!
Z43: Total Revenues | AB43: =SUM(AB39:AB42) -> #REF! | AC43: =SUM(AC39:AC42) -> #REF! | AD43: =SUM(AD39:AD42) -> #REF! | AE43: =SUM(AE39:AE42) -> #REF! | AF43: =SUM(AF39:AF42) -> #REF!
AB44: =AB43-#REF! -> #REF! | AC44: =#REF!-AC43 -> #REF! | AD44: =#REF!-AD43 -> #REF! | AE44: =#REF!-AE43 -> #REF! | AF44: =#REF!-AF43 -> #REF!
Z45: Gross Profit
Z46: =Z39 -> #REF! | AB46: =_xlfn.XLOOKUP(AB$37,#REF!,#REF!) -> #REF! | AC46: =_xlfn.XLOOKUP(AC$37,#REF!,#REF!) -> #REF! | AD46: =_xlfn.XLOOKUP(AD$37,#REF!,#REF!) -> #REF! | AE46: =_xlfn.XLOOKUP(AE$37,#REF!,#REF!) -> #REF! | AF46: =_xlfn.XLOOKUP(AF$37,#REF!,#REF!) -> #REF!
Z47: =Z40 -> #REF! | AB47: =_xlfn.XLOOKUP(AB$37,#REF!,#REF!) -> #REF! | AC47: =_xlfn.XLOOKUP(AC$37,#REF!,#REF!) -> #REF! | AD47: =_xlfn.XLOOKUP(AD$37,#REF!,#REF!) -> #REF! | AE47: =_xlfn.XLOOKUP(AE$37,#REF!,#REF!) -> #REF! | AF47: =_xlfn.XLOOKUP(AF$37,#REF!,#REF!) -> #REF!
Z48: =Z41 -> #REF! | AB48: =_xlfn.XLOOKUP(AB$37,#REF!,#REF!) -> #REF! | AC48: =_xlfn.XLOOKUP(AC$37,#REF!,#REF!) -> #REF! | AD48: =_xlfn.XLOOKUP(AD$37,#REF!,#REF!) -> #REF! | AE48: =_xlfn.XLOOKUP(AE$37,#REF!,#REF!) -> #REF! | AF48: =_xlfn.XLOOKUP(AF$37,#REF!,#REF!) -> #REF!
Z49: =Z42 -> #REF! | AB49: =_xlfn.XLOOKUP(AB$37,#REF!,#REF!) -> #REF! | AC49: =_xlfn.XLOOKUP(AC$37,#REF!,#REF!) -> #REF! | AD49: =_xlfn.XLOOKUP(AD$37,#REF!,#REF!) -> #REF! | AE49: =_xlfn.XLOOKUP(AE$37,#REF!,#REF!) -> #REF! | AF49: =_xlfn.XLOOKUP(AF$37,#REF!,#REF!) -> #REF!
Z50: Total Gross Profit | AB50: =SUM(AB46:AB49) -> #REF! | AC50: =SUM(AC46:AC49) -> #REF! | AD50: =SUM(AD46:AD49) -> #REF! | AE50: =SUM(AE46:AE49) -> #REF! | AF50: =SUM(AF46:AF49) -> #REF!
Z52: GP %
Z53: =Z46 -> #REF! | AB53: =AB46/AB39 -> #REF! | AC53: =AC46/AC39 -> #REF! | AD53: =AD46/AD39 -> #REF! | AE53: =AE46/AE39 -> #REF! | AF53: =AF46/AF39 -> #REF!
Z54: =Z47 -> #REF! | AB54: =AB47/AB40 -> #REF! | AC54: =AC47/AC40 -> #REF! | AD54: =AD47/AD40 -> #REF! | AE54: =AE47/AE40 -> #REF! | AF54: =AF47/AF40 -> #REF!
Z55: =Z48 -> #REF! | AB55: =AB48/AB41 -> #REF! | AC55: =AC48/AC41 -> #REF! | AD55: =AD48/AD41 -> #REF! | AE55: =AE48/AE41 -> #REF! | AF55: =AF48/AF41 -> #REF!
Z56: =Z49 -> #REF! | AB56: =AB49/AB42 -> #REF! | AC56: =AC49/AC42 -> #REF! | AD56: =AD49/AD42 -> #REF! | AE56: =AE49/AE42 -> #REF! | AF56: =AF49/AF42 -> #REF!
Z57: Total % of Revenue | AB57: =AB50/AB43 -> #REF! | AC57: =AC50/AC43 -> #REF! | AD57: =AD50/AD43 -> #REF! | AE57: =AE50/AE43 -> #REF! | AF57: =AF50/AF43 -> #REF!
Z59: % of Revenue
Z60: =Z39 -> #REF! | AB60: =AB39/AB$43 -> #REF! | AC60: =AC39/AC$43 -> #REF! | AD60: =AD39/AD$43 -> #REF! | AE60: =AE39/AE$43 -> #REF! | AF60: =AF39/AF$43 -> #REF!
Z61: =Z40 -> #REF! | AB61: =AB40/AB$43 -> #REF! | AC61: =AC40/AC$43 -> #REF! | AD61: =AD40/AD$43 -> #REF! | AE61: =AE40/AE$43 -> #REF! | AF61: =AF40/AF$43 -> #REF!
Z62: =Z41 -> #REF! | AB62: =AB41/AB$43 -> #REF! | AC62: =AC41/AC$43 -> #REF! | AD62: =AD41/AD$43 -> #REF! | AE62: =AE41/AE$43 -> #REF! | AF62: =AF41/AF$43 -> #REF!
Z63: =Z42 -> #REF! | AB63: =AB42/AB$43 -> #REF! | AC63: =AC42/AC$43 -> #REF! | AD63: =AD42/AD$43 -> #REF! | AE63: =AE42/AE$43 -> #REF! | AF63: =AF42/AF$43 -> #REF!
Z64: Total % of Revenue | AB64: =SUM(AB60:AB63) -> #REF! | AC64: =SUM(AC60:AC63) -> #REF! | AD64: =SUM(AD60:AD63) -> #REF! | AE64: =SUM(AE60:AE63) -> #REF! | AF64: =SUM(AF60:AF63) -> #REF!
Z66: SG&A, allocated by Revenue
Z67: =Z60 -> #REF! | AB67: =AB$71*AB60 -> #REF! | AC67: =AC$71*AC60 -> #REF! | AD67: =AD$71*AD60 -> #REF! | AE67: =AE$71*AE60 -> #REF! | AF67: =AF$71*AF60 -> #REF!
Z68: =Z61 -> #REF! | AB68: =AB$71*AB61 -> #REF! | AC68: =AC$71*AC61 -> #REF! | AD68: =AD$71*AD61 -> #REF! | AE68: =AE$71*AE61 -> #REF! | AF68: =AF$71*AF61 -> #REF!
Z69: =Z62 -> #REF! | AB69: =AB$71*AB62 -> #REF! | AC69: =AC$71*AC62 -> #REF! | AD69: =AD$71*AD62 -> #REF! | AE69: =AE$71*AE62 -> #REF! | AF69: =AF$71*AF62 -> #REF!
Z70: =Z63 -> #REF! | AB70: =AB$71*AB63 -> #REF! | AC70: =AC$71*AC63 -> #REF! | AD70: =AD$71*AD63 -> #REF! | AE70: =AE$71*AE63 -> #REF! | AF70: =AF$71*AF63 -> #REF!
Z71: Total SG&A | AB71: =_xlfn.XLOOKUP(AB$37,#REF!,#REF!) -> #REF! | AC71: =_xlfn.XLOOKUP(AC$37,#REF!,#REF!) -> #REF! | AD71: =_xlfn.XLOOKUP(AD$37,#REF!,#REF!) -> #REF! | AE71: =_xlfn.XLOOKUP(AE$37,#REF!,#REF!) -> #REF! | AF71: =_xlfn.XLOOKUP(AF$37,#REF!,#REF!) -> #REF!
Z73: EBITDA
Z74: =Z67 -> #REF! | AB74: =AB46-AB67 -> #REF! | AC74: =AC46-AC67 -> #REF! | AD74: =AD46-AD67 -> #REF! | AE74: =AE46-AE67 -> #REF! | AF74: =AF46-AF67 -> #REF!
Z75: =Z68 -> #REF! | AB75: =AB47-AB68 -> #REF! | AC75: =AC47-AC68 -> #REF! | AD75: =AD47-AD68 -> #REF! | AE75: =AE47-AE68 -> #REF! | AF75: =AF47-AF68 -> #REF!
Z76: =Z69 -> #REF! | AB76: =AB48-AB69 -> #REF! | AC76: =AC48-AC69 -> #REF! | AD76: =AD48-AD69 -> #REF! | AE76: =AE48-AE69 -> #REF! | AF76: =AF48-AF69 -> #REF!
Z77: =Z70 -> #REF! | AB77: =AB49-AB70 -> #REF! | AC77: =AC49-AC70 -> #REF! | AD77: =AD49-AD70 -> #REF! | AE77: =AE49-AE70 -> #REF! | AF77: =AF49-AF70 -> #REF!
Z78: Total EBITDA | AB78: =SUM(AB74:AB77) -> #REF! | AC78: =SUM(AC74:AC77) -> #REF! | AD78: =SUM(AD74:AD77) -> #REF! | AE78: =SUM(AE74:AE77) -> #REF! | AF78: =SUM(AF74:AF77) -> #REF!
AB79: =AB78-#REF! -> #REF! | AC79: =AC78-#REF! -> #REF! | AD79: =AD78-#REF! -> #REF! | AE79: =AE78-#REF! -> #REF! | AF79: =AF78-#REF! -> #REF!
Z81: Enterprise Value
Z82: =Z74 -> #REF! | AA82: 6.5 | AB82: =$AA82*AB74 -> #REF! | AC82: =$AA82*AC74 -> #REF! | AD82: =$AA82*AD74 -> #REF! | AE82: =$AA82*AE74 -> #REF! | AF82: =$AA82*AF74 -> #REF!
Z83: =Z75 -> #REF! | AA83: 6.25 | AB83: =$AA83*AB75 -> #REF! | AC83: =$AA83*AC75 -> #REF! | AD83: =$AA83*AD75 -> #REF! | AE83: =$AA83*AE75 -> #REF! | AF83: =$AA83*AF75 -> #REF!
Z84: =Z76 -> #REF! | AA84: 3.5 | AB84: =$AA84*AB76 -> #REF! | AC84: =$AA84*AC76 -> #REF! | AD84: =$AA84*AD76 -> #REF! | AE84: =$AA84*AE76 -> #REF! | AF84: =$AA84*AF76 -> #REF!
Z85: =Z77 -> #REF! | AA85: 4.5 | AB85: =$AA85*AB77 -> #REF! | AC85: =$AA85*AC77 -> #REF! | AD85: =$AA85*AD77 -> #REF! | AE85: =$AA85*AE77 -> #REF! | AF85: =$AA85*AF77 -> #REF!
Z86: Total EV | AB86: =SUM(AB82:AB85) -> #REF! | AC86: =SUM(AC82:AC85) -> #REF! | AD86: =SUM(AD82:AD85) -> #REF! | AE86: =SUM(AE82:AE85) -> #REF! | AF86: =SUM(AF82:AF85) -> #REF!

Sheet PB_CACHE
A1: H4sIAAAAAAAEAM2QvU7DMBSF3QZEEDyEdyIrKf2hQxYCAokORalYqqo41hWx6tjBdpDSx+gLgx2lMLAwcgffa0vnu8cHDRBCn65893U5dMfzkltW3iq1w6u2BoMXvNBUtxF+AW24kukoHk1JQmISRzhrhG00pBIaq6mI8LIpBGdP0K7UDmQqGyFOPT//xm477LbHkhw0p4LvaSEgo6yE3y9XK1Uv4ANEd7vjzDobThs47lnvKsxUVVMNOnykpsz5HlCAwsMgb42FimRKCOh0hjyAdBvYsd+/N26bbY+A12S97lW51Vy+RbgyTGnBi58Mxv77fwmgmM3ohE2myfx6DPHNfLMJh33c50E/nPjhP1r15i6+APaTkYMnAgAA

Sheet Model
B2: =H5& " LBO Model" -> LBO Model | AK2: x
B4: =+"Sources & Uses ($ in "& $H$11&")" -> Sources & Uses ($ in millions) | E4: General Assumptions | J4: Initial Valuation | R4: =I24 -> 46022 | S4: =J24 -> 46387
B5: Sources | E5: Company Name | J5: =_xlfn.CONCAT("Adj. EBITDA ","(",YEAR(H7),")") -> Adj. EBITDA (2025) | M5: =+$I$109 -> 4 | Q5: Adj. EBITDA x | R5: =+C11/I95 -> -30 | S5: =+C11/J95 -> 3.8408358
B6: SCF Equity | C6: =+C11-SUM(C7:C10) -> 70 | D6: =+C6/SUM($C$6:$C$7) -> 0.93333333 | E6: Circuit Breaker | H6: 1 | J6: Entry Multiple | M6: =+M7/M5 -> 37.5 | Q6: Leverage: | R6: =+(C10+C8)/I95 -> -15 | S6: =+C10/J95 -> 1.9204179
B7: Rolled Equity | C7: 5 | D7: =C7/SUM(C6:C7) -> 0.066666667 | E7: Last FY close date | H7: 46022 | J7: Enterprise Value | M7: =+C11 -> 150 | Q7: Revenue x | R7: =+C11/I39 -> 2.5 | S7: =+C11/J39 -> 2.4875622
B8: Seller Note | C8: 0 | E8: Expected close date | H8: 46295
B9: RCF Draw | C9: 0 | E9: Remaining Months in year after close | H9: =12-MONTH(H8-H7) -> 3 | J9: Less: Gross Debt | M9: 5.2
B10: Term Loan | C10: =D10*C11 -> 75 | D10: 0.5 | E10: Scenario (1=Base, 2=Mgmt., 3=Downside, 4=S.Q.) | H10: 2 | J10: Plus: Cash | M10: 35.7
B11: Total | C11: =+'Output AVP'!I5 -> 150 | E11: $ in | H11: millions
J12: Offer Value | M12: =+M7-M9+M10 -> 180.5
B13: Uses | E13: Selected Financial Assumptions
B14: Cash to Owners | C14: =+C20-SUM(C15:C19) -> 103.5 | E14: =J5 -> Adj. EBITDA (2025) | H14: =+$I$109 -> 4 | J14: Balance Sheet Check | M14: =SUM(I333:Q333) -> 272.35642 | R14: 2025 EBITDA | S14: 2026 EBITDA
B15: Rolled Equity | C15: 46.5 | E15: Cash Floor | H15: 1 | J15: Dividends? | M15: 1 | R15: 0 | S15: 0
B16: Seller Note | C16: =+C8 -> 0 | E16: Exit Multiple | H16: =CHOOSE($H$10,K18,L18,M18,K18) -> 3.8408358 | P16: 2025 EBITDA: | Q16: =+K95 -> 39.31054 | R16: for every | S16: for every
E17: Tax Rate | H17: 0.25 | K17: Base | L17: Upside | M17: Low | P17: 2026 EBITDA: | Q17: =+L95 -> 39.569645 | R17: 0 | S17: 0
E18: Depreciable Life | H18: 7 | J18: Exit Mult. | K18: =S5 -> 3.8408358 | L18: =K18 -> 3.8408358 | M18: 7 | R18: over (EBITDA) | S18: over (EBITDA)
E19: 2025 Earnout Paid in 2026 | H19: 0 | R19: 0 | S19: 0
B20: Total | C20: =+C11 -> 150 | E20: 2026 Earnout Paid in 2027 | H20: 0 | Q20: Cap (millions): | R20: 0 | S20: 0
A23: x | B23: Income Statement | Q23: CAGR | U23: Base Case Assumptions | AB23: Management Assumptions | AI23: Downside Assumptions | AP23: Status Quo Assumptions
B24: ="($ in "&$H$11&")" -> ($ in millions) | C24: =EOMONTH(D24,-12) -> 43830 | D24: =EOMONTH(E24,-12) -> 44196 | E24: =EOMONTH(F24,-12) -> 44561 | F24: =EOMONTH(G24,-12) -> 44926 | G24: =EOMONTH(H24,-12) -> 45291 | H24: =EOMONTH(I24,-12) -> 45657 | I24: =H7 -> 46022 | J24: =EOMONTH(I24,12) -> 46387 | K24: =EOMONTH(J24,12) -> 46752 | L24: =EOMONTH(K24,12) -> 47118 | M24: =EOMONTH(L24,12) -> 47483 | N24: =EOMONTH(M24,12) -> 47848 | O24: =EOMONTH(N24,12) -> 48213 | Q24: '24-'26 | R24: '26-'29 | S24: '24-'29 | U24: =+J24 -> 46387 | V24: =+EOMONTH(U24,12) -> 46752 | W24: =+EOMONTH(V24,12) -> 47118 | X24: =+EOMONTH(W24,12) -> 47483 | Y24: =+EOMONTH(X24,12) -> 47848 | Z24: =+EOMONTH(Y24,12) -> 48213 | AB24: =+U24 -> 46387 | AC24: =+EOMONTH(AB24,12) -> 46752 | AD24: =+EOMONTH(AC24,12) -> 47118 | AE24: =+EOMONTH(AD24,12) -> 47483 | AF24: =+EOMONTH(AE24,12) -> 47848 | AG24: =+EOMONTH(AF24,12) -> 48213 | AI24: =+AB24 -> 46387 | AJ24: =+EOMONTH(AI24,12) -> 46752 | AK24: =+EOMONTH(AJ24,12) -> 47118 | AL24: =+EOMONTH(AK24,12) -> 47483 | AM24: =+EOMONTH(AL24,12) -> 47848 | AN24: =+EOMONTH(AM24,12) -> 48213 | AP24: =+AI24 -> 46387 | AQ24: =+EOMONTH(AP24,12) -> 46752 | AR24: =+EOMONTH(AQ24,12) -> 47118 | AS24: =+EOMONTH(AR24,12) -> 47483 | AT24: =+EOMONTH(AS24,12) -> 47848 | AU24: =+EOMONTH(AT24,12) -> 48213
B26: Business Line 1 | F26: 10 | G26: 10 | H26: 10 | I26: 10 | J26: =I26*(1+J33) -> 10.1 | K26: =J26*(1+K33) -> 10.201 | L26: =K26*(1+L33) -> 10.30301 | M26: =L26*(1+M33) -> 10.40604 | N26: =M26*(1+N33) -> 10.510101 | O26: =N26*(1+O33) -> 10.615202
B27: Business Line 2 | F27: 10 | G27: 10 | H27: 10 | I27: 10 | J27: =I27*(1+J34) -> 10.1 | K27: =J27*(1+K34) -> 10.201 | L27: =K27*(1+L34) -> 10.30301 | M27: =L27*(1+M34) -> 10.40604 | N27: =M27*(1+N34) -> 10.510101 | O27: =N27*(1+O34) -> 10.615202
B28: Business Line 3 | F28: 10 | G28: 10 | H28: 10 | I28: 10 | J28: =I28*(1+J35) -> 10.1 | K28: =J28*(1+K35) -> 10.201 | L28: =K28*(1+L35) -> 10.30301 | M28: =L28*(1+M35) -> 10.40604 | N28: =M28*(1+N35) -> 10.510101 | O28: =N28*(1+O35) -> 10.615202
B29: Business Line 4 | F29: 10 | G29: 10 | H29: 10 | I29: 10 | J29: =I29*(1+J36) -> 10 | K29: =J29*(1+K36) -> 10 | L29: =K29*(1+L36) -> 10 | M29: =L29*(1+M36) -> 10 | N29: =M29*(1+N36) -> 10 | O29: =N29*(1+O36) -> 10
B30: Business Line 5 | F30: 10 | G30: 10 | H30: 10 | I30: 10 | J30: =I30*(1+J37) -> 10 | K30: =J30*(1+K37) -> 10 | L30: =K30*(1+L37) -> 10 | M30: =L30*(1+M37) -> 10 | N30: =M30*(1+N37) -> 10 | O30: =N30*(1+O37) -> 10
B31: Business Line 6 | F31: 10 | G31: 10 | H31: 10 | I31: 10 | J31: =I31*(1+J38) -> 10 | K31: =J31*(1+K38) -> 10 | L31: =K31*(1+L38) -> 10 | M31: =L31*(1+M38) -> 10 | N31: =M31*(1+N38) -> 10 | O31: =N31*(1+O38) -> 10
B33: =_xlfn.CONCAT(B26," ","Growth") -> Business Line 1 Growth | J33: =+CHOOSE($H$10,U33,AB33,AI33,AP33) -> 0.01 | K33: =+CHOOSE($H$10,V33,AC33,AJ33,AQ33) -> 0.01 | L33: =+CHOOSE($H$10,W33,AD33,AK33,AR33) -> 0.01 | M33: =+CHOOSE($H$10,X33,AE33,AL33,AS33) -> 0.01 | N33: =+CHOOSE($H$10,Y33,AF33,AM33,AT33) -> 0.01 | O33: =+CHOOSE($H$10,Z33,AG33,AN33,AU33) -> 0.01 | U33: 0.01 | V33: =U33 -> 0.01 | W33: 0.01 | X33: 0.01 | Y33: 0.01 | Z33: 0.01 | AB33: 0.01 | AC33: =AB33 -> 0.01 | AD33: 0.01 | AE33: 0.01 | AF33: 0.01 | AG33: 0.01
B34: =_xlfn.CONCAT(B27," ","Growth") -> Business Line 2 Growth | J34: =+CHOOSE($H$10,U34,AB34,AI34,AP34) -> 0.01 | K34: =+CHOOSE($H$10,V34,AC34,AJ34,AQ34) -> 0.01 | L34: =+CHOOSE($H$10,W34,AD34,AK34,AR34) -> 0.01 | M34: =+CHOOSE($H$10,X34,AE34,AL34,AS34) -> 0.01 | N34: =+CHOOSE($H$10,Y34,AF34,AM34,AT34) -> 0.01 | O34: =+CHOOSE($H$10,Z34,AG34,AN34,AU34) -> 0.01 | U34: 0.01 | V34: =U34 -> 0.01 | W34: 0.01 | X34: 0.01 | Y34: 0.01 | Z34: 0.01 | AB34: 0.01 | AC34: =AB34 -> 0.01 | AD34: 0.01 | AE34: 0.01 | AF34: 0.01 | AG34: 0.01
B35: =_xlfn.CONCAT(B28," ","Growth") -> Business Line 3 Growth | J35: =+CHOOSE($H$10,U35,AB35,AI35,AP35) -> 0.01 | K35: =+CHOOSE($H$10,V35,AC35,AJ35,AQ35) -> 0.01 | L35: =+CHOOSE($H$10,W35,AD35,AK35,AR35) -> 0.01 | M35: =+CHOOSE($H$10,X35,AE35,AL35,AS35) -> 0.01 | N35: =+CHOOSE($H$10,Y35,AF35,AM35,AT35) -> 0.01 | O35: =+CHOOSE($H$10,Z35,AG35,AN35,AU35) -> 0.01 | U35: 0.01 | V35: =U35 -> 0.01 | W35: 0.01 | X35: 0.01 | Y35: 0.01 | Z35: 0.01 | AB35: 0.01 | AC35: =AB35 -> 0.01 | AD35: 0.01 | AE35: 0.01 | AF35: 0.01 | AG35: 0.01
B36: =_xlfn.CONCAT(B29," ","Growth") -> Business Line 4 Growth | J36: =+CHOOSE($H$10,U36,AB36,AI36,AP36) -> 0 | K36: =+CHOOSE($H$10,V36,AC36,AJ36,AQ36) -> 0 | L36: =+CHOOSE($H$10,W36,AD36,AK36,AR36) -> 0 | M36: =+CHOOSE($H$10,X36,AE36,AL36,AS36) -> 0 | N36: =+CHOOSE($H$10,Y36,AF36,AM36,AT36) -> 0 | O36: =+CHOOSE($H$10,Z36,AG36,AN36,AU36) -> 0
B37: =_xlfn.CONCAT(B30," ","Growth") -> Business Line 5 Growth | J37: =+CHOOSE($H$10,U37,AB37,AI37,AP37) -> 0 | K37: =+CHOOSE($H$10,V37,AC37,AJ37,AQ37) -> 0 | L37: =+CHOOSE($H$10,W37,AD37,AK37,AR37) -> 0 | M37: =+CHOOSE($H$10,X37,AE37,AL37,AS37) -> 0 | N37: =+CHOOSE($H$10,Y37,AF37,AM37,AT37) -> 0 | O37: =+CHOOSE($H$10,Z37,AG37,AN37,AU37) -> 0
B38: =_xlfn.CONCAT(B31," ","Growth") -> Business Line 6 Growth | J38: =+CHOOSE($H$10,U38,AB38,AI38,AP38) -> 0 | K38: =+CHOOSE($H$10,V38,AC38,AJ38,AQ38) -> 0 | L38: =+CHOOSE($H$10,W38,AD38,AK38,AR38) -> 0 | M38: =+CHOOSE($H$10,X38,AE38,AL38,AS38) -> 0 | N38: =+CHOOSE($H$10,Y38,AF38,AM38,AT38) -> 0 | O38: =+CHOOSE($H$10,Z38,AG38,AN38,AU38) -> 0
B39: Revenue | F39: =SUM(F26:F32) -> 60 | G39: =SUM(G26:G32) -> 60 | H39: =SUM(H26:H32) -> 60 | I39: =SUM(I26:I32) -> 60 | J39: =SUM(J26:J32) -> 60.3 | K39: =SUM(K26:K32) -> 60.603 | L39: =SUM(L26:L32) -> 60.90903 | M39: =SUM(M26:M32) -> 61.21812 | ... O39: =SUM(O26:O32) -> 61.845605 | Q39: =+IFERROR(((L39/J39)^(1/(2026-2024)))-1,"n/a") -> 0.0050373127 | R39: =+IFERROR(((O39/L39)^(1/(2029-2026)))-1,"n/a") -> 0.0050994883 | S39: =+IFERROR(((O39/J39)^(1/(2029-2024)))-1,"n/a") -> 0.0050746176
B40: Total Revenue Growth % | G40: =+G39/F39-1 -> 0 | H40: =+H39/G39-1 -> 0 | I40: =+I39/H39-1 -> 0 | J40: =+J39/I39-1 -> 0.005 | K40: =+K39/J39-1 -> 0.0050248756 | L40: =+L39/K39-1 -> 0.00504975 | M40: =+M39/L39-1 -> 0.0050746219 | N40: =+N39/M39-1 -> 0.0050994902 | O40: =+O39/N39-1 -> 0.0051243535 | U40: 0.01 | V40: =U40 -> 0.01 | W40: 0.01 | X40: 0.01 | Y40: 0.01 | Z40: 0.01
B42: COGS 1 | F42: 5 | G42: 5 | H42: 5 | I42: 5 | J42: =J52*J$39 -> 0.603 | K42: =K52*K$39 -> 0.60603 | L42: =L52*L$39 -> 0.6090903 | M42: =M52*M$39 -> 0.6121812 | N42: =N52*N$39 -> 0.61530302 | O42: =O52*O$39 -> 0.61845605
B43: COGS 2 | F43: 5 | G43: 5 | H43: 5 | I43: 5 | J43: =J53*J$39 -> 0.603 | K43: =K53*K$39 -> 0.60603 | L43: =L53*L$39 -> 0.6090903 | M43: =M53*M$39 -> 0.6121812 | N43: =N53*N$39 -> 0.61530302 | O43: =O53*O$39 -> 0.61845605
B44: COGS 3 | F44: 5 | G44: 5 | H44: 5 | I44: 5 | J44: =J54*J$39 -> 0 | K44: =K54*K$39 -> 0 | L44: =L54*L$39 -> 0 | M44: =M54*M$39 -> 0 | N44: =N54*N$39 -> 0 | O44: =O54*O$39 -> 0
B45: COGS 4 | F45: 5 | G45: 5 | H45: 5 | I45: 5 | J45: =J55*J$39 -> 0 | K45: =K55*K$39 -> 0 | L45: =L55*L$39 -> 0 | M45: =M55*M$39 -> 0 | N45: =N55*N$39 -> 0 | O45: =O55*O$39 -> 0
B46: COGS 5 | F46: 5 | G46: 5 | H46: 5 | I46: 5 | J46: =J56*J$39 -> 0 | K46: =K56*K$39 -> 0 | L46: =L56*L$39 -> 0 | M46: =M56*M$39 -> 0 | N46: =N56*N$39 -> 0 | O46: =O56*O$39 -> 0
B47: COGS 6 | F47: 5 | G47: 5 | H47: 5 | I47: 5 | J47: =J57*J$39 -> 0 | K47: =K57*K$39 -> 0 | L47: =L57*L$39 -> 0 | M47: =M57*M$39 -> 0 | N47: =N57*N$39 -> 0 | O47: =O57*O$39 -> 0
B48: COGS 7 | F48: 5 | G48: 5 | H48: 5 | I48: 5 | J48: =J58*J$39 -> 0 | K48: =K58*K$39 -> 0 | L48: =L58*L$39 -> 0 | M48: =M58*M$39 -> 0 | N48: =N58*N$39 -> 0 | O48: =O58*O$39 -> 0
B49: COGS 8 | F49: 5 | G49: 5 | H49: 5 | I49: 5 | J49: =J59*J$39 -> 0 | K49: =K59*K$39 -> 0 | L49: =L59*L$39 -> 0 | M49: =M59*M$39 -> 0 | N49: =N59*N$39 -> 0 | O49: =O59*O$39 -> 0
B50: COGS 9 | F50: 5 | G50: 5 | H50: 5 | I50: 5 | J50: =J60*J$39 -> 0 | K50: =K60*K$39 -> 0 | L50: =L60*L$39 -> 0 | M50: =M60*M$39 -> 0 | N50: =N60*N$39 -> 0 | O50: =O60*O$39 -> 0
B52: =_xlfn.CONCAT(B42," ","% of rev.") -> COGS 1 % of rev. | J52: =+CHOOSE($H$10,U52,AB52,AI52,AP52) -> 0.01 | K52: =+CHOOSE($H$10,V52,AC52,AJ52,AQ52) -> 0.01 | L52: =+CHOOSE($H$10,W52,AD52,AK52,AR52) -> 0.01 | M52: =+CHOOSE($H$10,X52,AE52,AL52,AS52) -> 0.01 | N52: =+CHOOSE($H$10,Y52,AF52,AM52,AT52) -> 0.01 | O52: =+CHOOSE($H$10,Z52,AG52,AN52,AU52) -> 0.01 | U52: 0.01 | V52: =U52 -> 0.01 | W52: 0.01 | X52: 0.01 | Y52: 0.01 | Z52: 0.01 | AB52: 0.01 | AC52: =AB52 -> 0.01 | AD52: 0.01 | AE52: 0.01 | AF52: 0.01 | AG52: 0.01
B53: =_xlfn.CONCAT(B43," ","% of rev.") -> COGS 2 % of rev. | J53: =+CHOOSE($H$10,U53,AB53,AI53,AP53) -> 0.01 | K53: =+CHOOSE($H$10,V53,AC53,AJ53,AQ53) -> 0.01 | L53: =+CHOOSE($H$10,W53,AD53,AK53,AR53) -> 0.01 | M53: =+CHOOSE($H$10,X53,AE53,AL53,AS53) -> 0.01 | N53: =+CHOOSE($H$10,Y53,AF53,AM53,AT53) -> 0.01 | O53: =+CHOOSE($H$10,Z53,AG53,AN53,AU53) -> 0.01 | U53: 0.01 | V53: =U53 -> 0.01 | W53: 0.01 | X53: 0.01 | Y53: 0.01 | Z53: 0.01 | AB53: 0.01 | AC53: =AB53 -> 0.01 | AD53: 0.01 | AE53: 0.01 | AF53: 0.01 | AG53: 0.01
B54: =_xlfn.CONCAT(B44," ","% of rev.") -> COGS 3 % of rev. | J54: =+CHOOSE($H$10,U54,AB54,AI54,AP54) -> 0 | K54: =+CHOOSE($H$10,V54,AC54,AJ54,AQ54) -> 0 | L54: =+CHOOSE($H$10,W54,AD54,AK54,AR54) -> 0 | M54: =+CHOOSE($H$10,X54,AE54,AL54,AS54) -> 0 | N54: =+CHOOSE($H$10,Y54,AF54,AM54,AT54) -> 0 | O54: =+CHOOSE($H$10,Z54,AG54,AN54,AU54) -> 0
B55: =_xlfn.CONCAT(B45," ","% of rev.") -> COGS 4 % of rev. | J55: =+CHOOSE($H$10,U55,AB55,AI55,AP55) -> 0 | K55: =+CHOOSE($H$10,V55,AC55,AJ55,AQ55) -> 0 | L55: =+CHOOSE($H$10,W55,AD55,AK55,AR55) -> 0 | M55: =+CHOOSE($H$10,X55,AE55,AL55,AS55) -> 0 | N55: =+CHOOSE($H$10,Y55,AF55,AM55,AT55) -> 0 | O55: =+CHOOSE($H$10,Z55,AG55,AN55,AU55) -> 0
B56: =_xlfn.CONCAT(B46," ","% of rev.") -> COGS 5 % of rev. | J56: =+CHOOSE($H$10,U56,AB56,AI56,AP56) -> 0 | K56: =+CHOOSE($H$10,V56,AC56,AJ56,AQ56) -> 0 | L56: =+CHOOSE($H$10,W56,AD56,AK56,AR56) -> 0 | M56: =+CHOOSE($H$10,X56,AE56,AL56,AS56) -> 0 | N56: =+CHOOSE($H$10,Y56,AF56,AM56,AT56) -> 0 | O56: =+CHOOSE($H$10,Z56,AG56,AN56,AU56) -> 0
B57: =_xlfn.CONCAT(B47," ","% of rev.") -> COGS 6 % of rev. | J57: =+CHOOSE($H$10,U57,AB57,AI57,AP57) -> 0 | K57: =+CHOOSE($H$10,V57,AC57,AJ57,AQ57) -> 0 | L57: =+CHOOSE($H$10,W57,AD57,AK57,AR57) -> 0 | M57: =+CHOOSE($H$10,X57,AE57,AL57,AS57) -> 0 | N57: =+CHOOSE($H$10,Y57,AF57,AM57,AT57) -> 0 | O57: =+CHOOSE($H$10,Z57,AG57,AN57,AU57) -> 0
B58: =_xlfn.CONCAT(B48," ","% of rev.") -> COGS 7 % of rev. | J58: =+CHOOSE($H$10,U58,AB58,AI58,AP58) -> 0 | K58: =+CHOOSE($H$10,V58,AC58,AJ58,AQ58) -> 0 | L58: =+CHOOSE($H$10,W58,AD58,AK58,AR58) -> 0 | M58: =+CHOOSE($H$10,X58,AE58,AL58,AS58) -> 0 | N58: =+CHOOSE($H$10,Y58,AF58,AM58,AT58) -> 0 | O58: =+CHOOSE($H$10,Z58,AG58,AN58,AU58) -> 0
B59: =_xlfn.CONCAT(B49," ","% of rev.") -> COGS 8 % of rev. | J59: =+CHOOSE($H$10,U59,AB59,AI59,AP59) -> 0 | K59: =+CHOOSE($H$10,V59,AC59,AJ59,AQ59) -> 0 | L59: =+CHOOSE($H$10,W59,AD59,AK59,AR59) -> 0 | M59: =+CHOOSE($H$10,X59,AE59,AL59,AS59) -> 0 | N59: =+CHOOSE($H$10,Y59,AF59,AM59,AT59) -> 0 | O59: =+CHOOSE($H$10,Z59,AG59,AN59,AU59) -> 0
B60: =_xlfn.CONCAT(B50," ","% of rev.") -> COGS 9 % of rev. | J60: =+CHOOSE($H$10,U60,AB60,AI60,AP60) -> 0 | K60: =+CHOOSE($H$10,V60,AC60,AJ60,AQ60) -> 0 | L60: =+CHOOSE($H$10,W60,AD60,AK60,AR60) -> 0 | M60: =+CHOOSE($H$10,X60,AE60,AL60,AS60) -> 0 | N60: =+CHOOSE($H$10,Y60,AF60,AM60,AT60) -> 0 | O60: =+CHOOSE($H$10,Z60,AG60,AN60,AU60) -> 0
B61: Total COGS | F61: =SUM(F42:F51) -> 45 | G61: =SUM(G42:G51) -> 45 | H61: =SUM(H42:H51) -> 45 | I61: =SUM(I42:I51) -> 45 | J61: =SUM(J42:J51) -> 1.206 | K61: =SUM(K42:K51) -> 1.21206 | L61: =SUM(L42:L51) -> 1.2181806 | M61: =SUM(M42:M51) -> 1.2243624 | ... O61: =SUM(O42:O51) -> 1.2369121
B62: Gross Margin | F62: =F39-F61 -> 15 | G62: =G39-G61 -> 15 | H62: =H39-H61 -> 15 | I62: =I39-I61 -> 15 | J62: =J39-J61 -> 59.094 | K62: =K39-K61 -> 59.39094 | L62: =L39-L61 -> 59.690849 | M62: =M39-M61 -> 59.993758 | ... O62: =O39-O61 -> 60.608692 | Q62: =+IFERROR(((L62/J62)^(1/(2026-2024)))-1,"n/a") -> 0.0050373127 | R62: =+IFERROR(((O62/L62)^(1/(2029-2026)))-1,"n/a") -> 0.0050994883 | S62: =+IFERROR(((O62/J62)^(1/(2029-2024)))-1,"n/a") -> 0.0050746176
B63: Gross Margin % | F63: =+F62/F39 -> 0.25 | G63: =+G62/G39 -> 0.25 | H63: =+H62/H39 -> 0.25 | I63: =+I62/I39 -> 0.25 | J63: =J62/J39 -> 0.98 | K63: =K62/K39 -> 0.98 | L63: =L62/L39 -> 0.98 | M63: =M62/M39 -> 0.98 | N63: =N62/N39 -> 0.98 | O63: =O62/O39 -> 0.98 | U63: =AVERAGE(F63:I63) -> 0.25 | V63: =U63 -> 0.25 | W63: =V63 -> 0.25 | X63: =W63 -> 0.25 | Y63: =X63 -> 0.25 | Z63: =Y63 -> 0.25
B65: SG&A 1 | F65: 2 | G65: 2 | H65: 2 | I65: 2 | J65: =I65*(1+J78) -> 2.02 | K65: =J65*(1+K78) -> 2.0402 | L65: =K65*(1+L78) -> 2.060602 | M65: =L65*(1+M78) -> 2.081208 | N65: =M65*(1+N78) -> 2.1020201 | O65: =N65*(1+O78) -> 2.1230403
B66: SG&A 2 | F66: 2 | G66: 2 | H66: 2 | I66: 2 | J66: =I66*(1+J79) -> 2.02 | K66: =J66*(1+K79) -> 2.0402 | L66: =K66*(1+L79) -> 2.060602 | M66: =L66*(1+M79) -> 2.081208 | N66: =M66*(1+N79) -> 2.1020201 | O66: =N66*(1+O79) -> 2.1230403
B67: SG&A 3 | F67: 2 | G67: 2 | H67: 2 | I67: 2 | J67: =I67*(1+J80) -> 2 | K67: =J67*(1+K80) -> 2 | L67: =K67*(1+L80) -> 2 | M67: =L67*(1+M80) -> 2 | N67: =M67*(1+N80) -> 2 | O67: =N67*(1+O80) -> 2
B68: SG&A 4 | F68: 2 | G68: 2 | H68: 2 | I68: 2 | J68: =I68*(1+J81) -> 2 | K68: =J68*(1+K81) -> 2 | L68: =K68*(1+L81) -> 2 | M68: =L68*(1+M81) -> 2 | N68: =M68*(1+N81) -> 2 | O68: =N68*(1+O81) -> 2
B69: SG&A 5 | F69: 2 | G69: 2 | H69: 2 | I69: 2 | J69: =I69*(1+J82) -> 2 | K69: =J69*(1+K82) -> 2 | L69: =K69*(1+L82) -> 2 | M69: =L69*(1+M82) -> 2 | N69: =M69*(1+N82) -> 2 | O69: =N69*(1+O82) -> 2
B70: SG&A 6 | F70: 2 | G70: 2 | H70: 2 | I70: 2 | J70: =I70*(1+J83) -> 2 | K70: =J70*(1+K83) -> 2 | L70: =K70*(1+L83) -> 2 | M70: =L70*(1+M83) -> 2 | N70: =M70*(1+N83) -> 2 | O70: =N70*(1+O83) -> 2
B71: SG&A 7 | F71: 2 | G71: 2 | H71: 2 | I71: 2 | J71: =I71*(1+J84) -> 2 | K71: =J71*(1+K84) -> 2 | L71: =K71*(1+L84) -> 2 | M71: =L71*(1+M84) -> 2 | N71: =M71*(1+N84) -> 2 | O71: =N71*(1+O84) -> 2
B72: SG&A 8 | F72: 2 | G72: 2 | H72: 2 | I72: 2 | J72: =I72*(1+J85) -> 2 | K72: =J72*(1+K85) -> 2 | L72: =K72*(1+L85) -> 2 | M72: =L72*(1+M85) -> 2 | N72: =M72*(1+N85) -> 2 | O72: =N72*(1+O85) -> 2
B73: SG&A 9 | F73: 2 | G73: 2 | H73: 2 | I73: 2 | J73: =I73*(1+J86) -> 2 | K73: =J73*(1+K86) -> 2 | L73: =K73*(1+L86) -> 2 | M73: =L73*(1+M86) -> 2 | N73: =M73*(1+N86) -> 2 | O73: =N73*(1+O86) -> 2
B74: SG&A 10 | F74: 2 | G74: 2 | H74: 2 | I74: 2 | J74: =I74*(1+J87) -> 2 | K74: =J74*(1+K87) -> 2 | L74: =K74*(1+L87) -> 2 | M74: =L74*(1+M87) -> 2 | N74: =M74*(1+N87) -> 2 | O74: =N74*(1+O87) -> 2
B78: =_xlfn.CONCAT(B65," ","Growth") -> SG&A 1 Growth | J78: =+CHOOSE($H$10,U78,AB78,AI78,AP78) -> 0.01 | K78: =+CHOOSE($H$10,V78,AC78,AJ78,AQ78) -> 0.01 | L78: =+CHOOSE($H$10,W78,AD78,AK78,AR78) -> 0.01 | M78: =+CHOOSE($H$10,X78,AE78,AL78,AS78) -> 0.01 | N78: =+CHOOSE($H$10,Y78,AF78,AM78,AT78) -> 0.01 | O78: =+CHOOSE($H$10,Z78,AG78,AN78,AU78) -> 0.01 | U78: 0.01 | V78: =U78 -> 0.01 | W78: 0.01 | X78: 0.01 | Y78: 0.01 | Z78: 0.01 | AB78: 0.01 | AC78: =AB78 -> 0.01 | AD78: 0.01 | AE78: 0.01 | AF78: 0.01 | AG78: 0.01
B79: =_xlfn.CONCAT(B66," ","Growth") -> SG&A 2 Growth | J79: =+CHOOSE($H$10,U79,AB79,AI79,AP79) -> 0.01 | K79: =+CHOOSE($H$10,V79,AC79,AJ79,AQ79) -> 0.01 | L79: =+CHOOSE($H$10,W79,AD79,AK79,AR79) -> 0.01 | M79: =+CHOOSE($H$10,X79,AE79,AL79,AS79) -> 0.01 | N79: =+CHOOSE($H$10,Y79,AF79,AM79,AT79) -> 0.01 | O79: =+CHOOSE($H$10,Z79,AG79,AN79,AU79) -> 0.01 | U79: 0.01 | V79: =U79 -> 0.01 | W79: 0.01 | X79: 0.01 | Y79: 0.01 | Z79: 0.01 | AB79: 0.01 | AC79: =AB79 -> 0.01 | AD79: 0.01 | AE79: 0.01 | AF79: 0.01 | AG79: 0.01
B80: =_xlfn.CONCAT(B67," ","Growth") -> SG&A 3 Growth | J80: =+CHOOSE($H$10,U80,AB80,AI80,AP80) -> 0 | K80: =+CHOOSE($H$10,V80,AC80,AJ80,AQ80) -> 0 | L80: =+CHOOSE($H$10,W80,AD80,AK80,AR80) -> 0 | M80: =+CHOOSE($H$10,X80,AE80,AL80,AS80) -> 0 | N80: =+CHOOSE($H$10,Y80,AF80,AM80,AT80) -> 0 | O80: =+CHOOSE($H$10,Z80,AG80,AN80,AU80) -> 0
B81: =_xlfn.CONCAT(B68," ","Growth") -> SG&A 4 Growth | J81: =+CHOOSE($H$10,U81,AB81,AI81,AP81) -> 0 | K81: =+CHOOSE($H$10,V81,AC81,AJ81,AQ81) -> 0 | L81: =+CHOOSE($H$10,W81,AD81,AK81,AR81) -> 0 | M81: =+CHOOSE($H$10,X81,AE81,AL81,AS81) -> 0 | N81: =+CHOOSE($H$10,Y81,AF81,AM81,AT81) -> 0 | O81: =+CHOOSE($H$10,Z81,AG81,AN81,AU81) -> 0
B82: =_xlfn.CONCAT(B69," ","Growth") -> SG&A 5 Growth | J82: =+CHOOSE($H$10,U82,AB82,AI82,AP82) -> 0 | K82: =+CHOOSE($H$10,V82,AC82,AJ82,AQ82) -> 0 | L82: =+CHOOSE($H$10,W82,AD82,AK82,AR82) -> 0 | M82: =+CHOOSE($H$10,X82,AE82,AL82,AS82) -> 0 | N82: =+CHOOSE($H$10,Y82,AF82,AM82,AT82) -> 0 | O82: =+CHOOSE($H$10,Z82,AG82,AN82,AU82) -> 0
B83: =_xlfn.CONCAT(B70," ","Growth") -> SG&A 6 Growth | J83: =+CHOOSE($H$10,U83,AB83,AI83,AP83) -> 0 | K83: =+CHOOSE($H$10,V83,AC83,AJ83,AQ83) -> 0 | L83: =+CHOOSE($H$10,W83,AD83,AK83,AR83) -> 0 | M83: =+CHOOSE($H$10,X83,AE83,AL83,AS83) -> 0 | N83: =+CHOOSE($H$10,Y83,AF83,AM83,AT83) -> 0 | O83: =+CHOOSE($H$10,Z83,AG83,AN83,AU83) -> 0
B84: =_xlfn.CONCAT(B71," ","Growth") -> SG&A 7 Growth | J84: =+CHOOSE($H$10,U84,AB84,AI84,AP84) -> 0 | K84: =+CHOOSE($H$10,V84,AC84,AJ84,AQ84) -> 0 | L84: =+CHOOSE($H$10,W84,AD84,AK84,AR84) -> 0 | M84: =+CHOOSE($H$10,X84,AE84,AL84,AS84) -> 0 | N84: =+CHOOSE($H$10,Y84,AF84,AM84,AT84) -> 0 | O84: =+CHOOSE($H$10,Z84,AG84,AN84,AU84) -> 0
B85: =_xlfn.CONCAT(B72," ","Growth") -> SG&A 8 Growth | J85: =+CHOOSE($H$10,U85,AB85,AI85,AP85) -> 0 | K85: =+CHOOSE($H$10,V85,AC85,AJ85,AQ85) -> 0 | L85: =+CHOOSE($H$10,W85,AD85,AK85,AR85) -> 0 | M85: =+CHOOSE($H$10,X85,AE85,AL85,AS85) -> 0 | N85: =+CHOOSE($H$10,Y85,AF85,AM85,AT85) -> 0 | O85: =+CHOOSE($H$10,Z85,AG85,AN85,AU85) -> 0
B86: =_xlfn.CONCAT(B73," ","Growth") -> SG&A 9 Growth | J86: =+CHOOSE($H$10,U86,AB86,AI86,AP86) -> 0 | K86: =+CHOOSE($H$10,V86,AC86,AJ86,AQ86) -> 0 | L86: =+CHOOSE($H$10,W86,AD86,AK86,AR86) -> 0 | M86: =+CHOOSE($H$10,X86,AE86,AL86,AS86) -> 0 | N86: =+CHOOSE($H$10,Y86,AF86,AM86,AT86) -> 0 | O86: =+CHOOSE($H$10,Z86,AG86,AN86,AU86) -> 0
B87: =_xlfn.CONCAT(B74," ","Growth") -> SG&A 10 Growth | J87: =+CHOOSE($H$10,U87,AB87,AI87,AP87) -> 0 | K87: =+CHOOSE($H$10,V87,AC87,AJ87,AQ87) -> 0 | L87: =+CHOOSE($H$10,W87,AD87,AK87,AR87) -> 0 | M87: =+CHOOSE($H$10,X87,AE87,AL87,AS87) -> 0 | N87: =+CHOOSE($H$10,Y87,AF87,AM87,AT87) -> 0 | O87: =+CHOOSE($H$10,Z87,AG87,AN87,AU87) -> 0
B88: Total Operating Costs | F88: =SUM(F65:F77) -> 20 | G88: =SUM(G65:G77) -> 20 | H88: =SUM(H65:H77) -> 20 | I88: =SUM(I65:I77) -> 20 | J88: =SUM(J65:J77) -> 20.04 | K88: =SUM(K65:K77) -> 20.0804 | L88: =SUM(L65:L77) -> 20.121204 | M88: =SUM(M65:M77) -> 20.162416 | ... O88: =SUM(O65:O77) -> 20.246081
B89: Opex % of Revenue | F89: =+F88/F39 -> 0.33333333 | G89: =+G88/G39 -> 0.33333333 | H89: =+H88/H39 -> 0.33333333 | I89: =+I88/I39 -> 0.33333333 | J89: =+J88/J39 -> 0.33233831 | K89: =+K88/K39 -> 0.33134333 | L89: =+L88/L39 -> 0.33034846 | M89: =+M88/M39 -> 0.32935373 | ... O89: =+O88/O39 -> 0.32736491 | U89: =AVERAGE(F89:I89) -> 0.33333333 | V89: =U89 -> 0.33333333 | W89: =V89 -> 0.33333333 | X89: =W89 -> 0.33333333 | Y89: =X89 -> 0.33333333 | Z89: =Y89 -> 0.33333333
B90: OI | F90: =F62-F88 -> -5 | G90: =G62-G88 -> -5 | H90: =H62-H88 -> -5 | I90: =I62-I88 -> -5 | J90: =J62-J88 -> 39.054 | K90: =K62-K88 -> 39.31054 | L90: =L62-L88 -> 39.569645 | M90: =M62-M88 -> 39.831342 | ... O90: =O62-O88 -> 40.362612
B91: =_xlfn.CONCAT(B90," ","Margin %") -> OI Margin % | F91: =F90/F39 -> -0.083333333 | G91: =G90/G39 -> -0.083333333 | H91: =H90/H39 -> -0.083333333 | I91: =I90/I39 -> -0.083333333 | J91: =J90/J39 -> 0.64766169 | K91: =K90/K39 -> 0.64865667 | L91: =L90/L39 -> 0.64965154 | M91: =M90/M39 -> 0.65064627 | ... O91: =O90/O39 -> 0.65263509
B94: Other Income | J94: =+CHOOSE($H$10,U94,AB94,AI94,AP94) -> 0 | K94: =+CHOOSE($H$10,V94,AC94,AJ94,AQ94) -> 0 | L94: =+CHOOSE($H$10,W94,AD94,AK94,AR94) -> 0 | M94: =+CHOOSE($H$10,X94,AE94,AL94,AS94) -> 0 | N94: =+CHOOSE($H$10,Y94,AF94,AM94,AT94) -> 0 | O94: =+CHOOSE($H$10,Z94,AG94,AN94,AU94) -> 0
B95: EBITDA | F95: =F90+SUM(F93:F94) -> -5 | G95: =G90+SUM(G93:G94) -> -5 | H95: =H90+SUM(H93:H94) -> -5 | I95: =I90+SUM(I93:I94) -> -5 | J95: =J90+SUM(J93:J94) -> 39.054 | K95: =K90+SUM(K93:K94) -> 39.31054 | L95: =L90+SUM(L93:L94) -> 39.569645 | M95: =M90+SUM(M93:M94) -> 39.831342 | ... O95: =O90+SUM(O93:O94) -> 40.362612 | Q95: =+IFERROR(((L95/J95)^(1/(2026-2024)))-1,"n/a") -> 0.0065800491 | R95: =+IFERROR(((O95/L95)^(1/(2029-2026)))-1,"n/a") -> 0.0066357908 | S95: =+IFERROR(((O95/J95)^(1/(2029-2024)))-1,"n/a") -> 0.0066134938
B96: =_xlfn.CONCAT(B95," ","Margin %") -> EBITDA Margin % | F96: =+F95/F$39 -> -0.083333333 | G96: =+G95/G$39 -> -0.083333333 | H96: =+H95/H$39 -> -0.083333333 | I96: =+I95/I$39 -> -0.083333333 | J96: =+J95/J$39 -> 0.64766169 | K96: =+K95/K$39 -> 0.64865667 | L96: =+L95/L$39 -> 0.64965154 | M96: =+M95/M$39 -> 0.65064627 | ... O96: =+O95/O$39 -> 0.65263509
U97: Include Adjustment?
B98: Adjustment 1 | F98: 1 | G98: 1 | H98: 1 | I98: 1 | U98: 1
B99: Adjustment 2 | F99: 1 | G99: 1 | H99: 1 | I99: 1 | U99: 1
B100: Adjustment 3 | F100: 1 | G100: 1 | H100: 1 | I100: 1 | U100: 1
B101: Adjustment 4 | F101: 1 | G101: 1 | H101: 1 | I101: 1 | U101: 1
B102: Adjustment 5 | F102: 1 | G102: 1 | H102: 1 | I102: 1 | U102: 1
B103: Adjustment 6 | F103: 1 | G103: 1 | H103: 1 | I103: 1 | U103: 1
B104: Adjustment 7 | F104: 1 | G104: 1 | H104: 1 | I104: 1 | U104: 1
B105: Adjustment 8 | F105: 1 | G105: 1 | H105: 1 | I105: 1 | U105: 1
B106: Adjustment 9 | F106: 1 | G106: 1 | H106: 1 | I106: 1 | U106: 1
B107: Adjustment 10 | F107: 1 | G107: 1 | H107: 1 | I107: 1 | U107: 0
B108: Total Adjustments | F108: =SUMPRODUCT(F98:F107,$U$98:$U$107) -> 9 | G108: =SUMPRODUCT(G98:G107,$U$98:$U$107) -> 9 | H108: =SUMPRODUCT(H98:H107,$U$98:$U$107) -> 9 | I108: =SUMPRODUCT(I98:I107,$U$98:$U$107) -> 9
A109: x | B109: Adj. EBITDA | F109: =F95+SUMPRODUCT(F98:F108,$U$98:$U$108) -> 4 | G109: =G95+SUMPRODUCT(G98:G108,$U$98:$U$108) -> 4 | H109: =H95+SUMPRODUCT(H98:H108,$U$98:$U$108) -> 4 | I109: =I95+SUMPRODUCT(I98:I108,$U$98:$U$108) -> 4 | J109: =J95+SUMPRODUCT(J98:J108,$U$98:$U$108) -> 39.054 | K109: =K95+SUMPRODUCT(K98:K108,$U$98:$U$108) -> 39.31054 | L109: =L95+SUMPRODUCT(L98:L108,$U$98:$U$108) -> 39.569645 | M109: =M95+SUMPRODUCT(M98:M108,$U$98:$U$108) -> 39.831342 | ... O109: =O95+SUMPRODUCT(O98:O108,$U$98:$U$108) -> 40.362612 | Q109: =+IFERROR(((L109/J109)^(1/(2026-2024)))-1,"n/a") -> 0.0065800491 | R109: =+IFERROR(((O109/L109)^(1/(2029-2026)))-1,"n/a") -> 0.0066357908 | S109: =+IFERROR(((O109/J109)^(1/(2029-2024)))-1,"n/a") -> 0.0066134938
B110: =_xlfn.CONCAT(B109," ","Margin %") -> Adj. EBITDA Margin % | F110: =+F109/F$39 -> 0.066666667 | G110: =+G109/G$39 -> 0.066666667 | H110: =+H109/H$39 -> 0.066666667 | I110: =+I109/I$39 -> 0.066666667 | J110: =+J109/J$39 -> 0.64766169 | K110: =+K109/K$39 -> 0.64865667 | L110: =+L109/L$39 -> 0.64965154 | M110: =+M109/M$39 -> 0.65064627 | ... O110: =+O109/O$39 -> 0.65263509
B112: Less: D&A | J112: =-J156 -> 0.17228571 | K112: =-K156 -> 0.34543714 | L112: =-L156 -> 0.51946294 | M112: =-M156 -> 0.69437186 | N112: =-N156 -> 0.87017272 | O112: =-O156 -> 1.0468744
B113: EBIT | J113: =+J109-J112 -> 38.881714 | K113: =+K109-K112 -> 38.965103 | L113: =+L109-L112 -> 39.050182 | M113: =+M109-M112 -> 39.13697 | N113: =+N109-N112 -> 39.225483 | O113: =+O109-O112 -> 39.315737
B115: Less: Interest Expense (Income) | J115: =IF($H$6=0,0,-(J205+J243)) -> 1.7005219 | K115: =IF($H$6=0,0,-(K205+K243)) -> 5.7496321 | L115: =IF($H$6=0,0,-(L205+L243)) -> 4.640625 | M115: =IF($H$6=0,0,-(M205+M243)) -> 3.7566964 | N115: =IF($H$6=0,0,-(N205+N243)) -> 2.8727679 | O115: =IF($H$6=0,0,-(Q205+Q243)) -> 1.9888393
B116: EBT | J116: =+J113-J115 -> 37.181192 | K116: =+K113-K115 -> 33.215471 | L116: =+L113-L115 -> 34.409557 | M116: =+M113-M115 -> 35.380274 | N116: =+N113-N115 -> 36.352715 | O116: =+O113-O115 -> 37.326898
...

Sheet P&L (presentation)
B2: =Model!B2 -> LBO Model
A4: x | B4: Income Statement | Q4: CAGR
B5: =Model!B24 -> ($ in millions) | C5: 43100 | D5: =EOMONTH(C5,12) -> 43465 | E5: =EOMONTH(D5,12) -> 43830 | F5: =EOMONTH(E5,12) -> 44196 | G5: =EOMONTH(F5,12) -> 44561 | H5: =EOMONTH(G5,12) -> 44926 | I5: =EOMONTH(H5,12) -> 45291 | J5: =EOMONTH(I5,12) -> 45657 | K5: =EOMONTH(J5,12) -> 46022 | ... O5: =EOMONTH(N5,12) -> 47483 | Q5: '24-'26 | R5: '26-'29 | S5: '24-'29
B7: Revenue | F7: =+Model!F39 -> 60 | G7: =+Model!G39 -> 60 | H7: =+Model!H39 -> 60 | I7: =+Model!I39 -> 60 | J7: =+Model!J39 -> 60.3 | K7: =+Model!K39 -> 60.603 | L7: =+Model!L39 -> 60.90903 | M7: =+Model!M39 -> 61.21812 | ... O7: =+Model!O39 -> 61.845605 | Q7: =+IFERROR(((L7/J7)^(1/(2026-2024)))-1,"n/a") -> 0.0050373127 | R7: =+IFERROR(((O7/L7)^(1/(2029-2026)))-1,"n/a") -> 0.0050994883 | S7: =+IFERROR(((O7/J7)^(1/(2029-2024)))-1,"n/a") -> 0.0050746176
B8: Total Revenue Growth % | G8: =+G7/F7-1 -> 0 | H8: =+H7/G7-1 -> 0 | I8: =+I7/H7-1 -> 0 | J8: =+J7/I7-1 -> 0.005 | K8: =+K7/J7-1 -> 0.0050248756 | L8: =+L7/K7-1 -> 0.00504975 | M8: =+M7/L7-1 -> 0.0050746219 | N8: =+N7/M7-1 -> 0.0050994902 | O8: =+O7/N7-1 -> 0.0051243535
B10: COGS | F10: =Model!F61 -> 45 | G10: =Model!G61 -> 45 | H10: =Model!H61 -> 45 | I10: =Model!I61 -> 45 | J10: =Model!J61 -> 1.206 | K10: =Model!K61 -> 1.21206 | L10: =Model!L61 -> 1.2181806 | M10: =Model!M61 -> 1.2243624 | ... O10: =Model!O61 -> 1.2369121
B11: Gross Margin | F11: =+F7-F10 -> 15 | G11: =+G7-G10 -> 15 | H11: =+H7-H10 -> 15 | I11: =+I7-I10 -> 15 | J11: =+J7-J10 -> 59.094 | K11: =+K7-K10 -> 59.39094 | L11: =+L7-L10 -> 59.690849 | M11: =+M7-M10 -> 59.993758 | ... O11: =+O7-O10 -> 60.608692 | Q11: =+IFERROR(((L11/J11)^(1/(2026-2024)))-1,"n/a") -> 0.0050373127 | R11: =+IFERROR(((O11/L11)^(1/(2029-2026)))-1,"n/a") -> 0.0050994883 | S11: =+IFERROR(((O11/J11)^(1/(2029-2024)))-1,"n/a") -> 0.0050746176
B12: Gross Margin % | F12: =+F11/F7 -> 0.25 | G12: =+G11/G7 -> 0.25 | H12: =+H11/H7 -> 0.25 | I12: =+I11/I7 -> 0.25 | J12: =+J11/J7 -> 0.98 | K12: =+K11/K7 -> 0.98 | L12: =+L11/L7 -> 0.98 | M12: =+M11/M7 -> 0.98 | ... O12: =+O11/O7 -> 0.98
B14: Operating Expenses | F14: =Model!F88 -> 20 | G14: =Model!G88 -> 20 | H14: =Model!H88 -> 20 | I14: =Model!I88 -> 20 | J14: =Model!J88 -> 20.04 | K14: =Model!K88 -> 20.0804 | L14: =Model!L88 -> 20.121204 | M14: =Model!M88 -> 20.162416 | ... O14: =Model!O88 -> 20.246081
B15: Opex % of Revenue | F15: =+F14/F7 -> 0.33333333 | G15: =+G14/G7 -> 0.33333333 | H15: =+H14/H7 -> 0.33333333 | I15: =+I14/I7 -> 0.33333333 | J15: =+J14/J7 -> 0.33233831 | K15: =+K14/K7 -> 0.33134333 | L15: =+L14/L7 -> 0.33034846 | M15: =+M14/M7 -> 0.32935373 | ... O15: =+O14/O7 -> 0.32736491
B16: Operating Income | F16: =+F11-F14 -> -5 | G16: =+G11-G14 -> -5 | H16: =+H11-H14 -> -5 | I16: =+I11-I14 -> -5 | J16: =+J11-J14 -> 39.054 | K16: =+K11-K14 -> 39.31054 | L16: =+L11-L14 -> 39.569645 | M16: =+M11-M14 -> 39.831342 | ... O16: =+O11-O14 -> 40.362612 | Q16: =+IFERROR(((L16/J16)^(1/(2026-2024)))-1,"n/a") -> 0.0065800491 | R16: =+IFERROR(((O16/L16)^(1/(2029-2026)))-1,"n/a") -> 0.0066357908 | S16: =+IFERROR(((O16/J16)^(1/(2029-2024)))-1,"n/a") -> 0.0066134938
B17: OI Margin % | F17: =+F16/F$7 -> -0.083333333 | G17: =+G16/G$7 -> -0.083333333 | H17: =+H16/H$7 -> -0.083333333 | I17: =+I16/I$7 -> -0.083333333 | J17: =+J16/J$7 -> 0.64766169 | K17: =+K16/K$7 -> 0.64865667 | L17: =+L16/L$7 -> 0.64965154 | M17: =+M16/M$7 -> 0.65064627 | ... O17: =+O16/O$7 -> 0.65263509
B19: Depreciation | F19: =Model!F93 -> 0 | G19: =Model!G93 -> 0 | H19: =Model!H93 -> 0 | I19: =Model!I93 -> 0 | J19: =Model!J93 -> 0 | K19: =Model!K93 -> 0 | L19: =Model!L93 -> 0 | M19: =Model!M93 -> 0 | ... O19: =Model!O93 -> 0
B20: Other Income | F20: =Model!F94 -> 0 | G20: =Model!G94 -> 0 | H20: =Model!H94 -> 0 | I20: =Model!I94 -> 0 | J20: =Model!J94 -> 0 | K20: =Model!K94 -> 0 | L20: =Model!L94 -> 0 | M20: =Model!M94 -> 0 | ... O20: =Model!O94 -> 0
B21: EBITDA | F21: =F16+SUM(F19:F20) -> -5 | G21: =G16+SUM(G19:G20) -> -5 | H21: =H16+SUM(H19:H20) -> -5 | I21: =I16+SUM(I19:I20) -> -5 | J21: =J16+SUM(J19:J20) -> 39.054 | K21: =K16+SUM(K19:K20) -> 39.31054 | L21: =L16+SUM(L19:L20) -> 39.569645 | M21: =M16+SUM(M19:M20) -> 39.831342 | ... O21: =O16+SUM(O19:O20) -> 40.362612
B22: EBITDA Margin % | F22: =F21/F7 -> -0.083333333 | G22: =G21/G7 -> -0.083333333 | H22: =H21/H7 -> -0.083333333 | I22: =I21/I7 -> -0.083333333 | J22: =J21/J7 -> 0.64766169 | K22: =K21/K7 -> 0.64865667 | L22: =L21/L7 -> 0.64965154 | M22: =M21/M7 -> 0.65064627 | ... O22: =O21/O7 -> 0.65263509
B24: Adjustments | F24: =+Model!F102 -> 1 | G24: =+Model!G102 -> 1 | H24: =+Model!H102 -> 1 | I24: =+Model!I102 -> 1 | J24: =+Model!J102 -> 0 | K24: =+Model!K102 -> 0 | L24: =+Model!L102 -> 0 | M24: =+Model!M102 -> 0 | ... O24: =+Model!O102 -> 0
A25: x | B25: Adj. EBITDA | F25: =+F21+F24 -> -4 | G25: =+G21+G24 -> -4 | H25: =+H21+H24 -> -4 | I25: =+I21+I24 -> -4 | J25: =+J21+J24 -> 39.054 | K25: =+K21+K24 -> 39.31054 | L25: =+L21+L24 -> 39.569645 | M25: =+M21+M24 -> 39.831342 | ... O25: =+O21+O24 -> 40.362612 | Q25: =+IFERROR(((L25/J25)^(1/(2026-2024)))-1,"n/a") -> 0.0065800491 | R25: =+IFERROR(((O25/L25)^(1/(2029-2026)))-1,"n/a") -> 0.0066357908 | S25: =+IFERROR(((O25/J25)^(1/(2029-2024)))-1,"n/a") -> 0.0066134938
B26: Adj. EBITDA Margin % | F26: =+F25/F$7 -> -0.066666667 | G26: =+G25/G$7 -> -0.066666667 | H26: =+H25/H$7 -> -0.066666667 | I26: =+I25/I$7 -> -0.066666667 | J26: =+J25/J$7 -> 0.64766169 | K26: =+K25/K$7 -> 0.64865667 | L26: =+L25/L$7 -> 0.64965154 | M26: =+M25/M$7 -> 0.65064627 | ... O26: =+O25/O$7 -> 0.65263509
B28: Maintenance Capex | F28: =Model!F121 -> 1 | G28: =Model!G121 -> 1 | H28: =Model!H121 -> 1 | I28: =Model!I121 -> 1 | J28: =Model!J121 -> 0.603 | K28: =Model!K121 -> 0.60603 | L28: =Model!L121 -> 0.6090903 | M28: =Model!M121 -> 0.6121812 | ... O28: =Model!O121 -> 0.61845605
B29: Growth Capex | F29: =Model!F122 -> 1 | G29: =Model!G122 -> 1 | H29: =Model!H122 -> 1 | I29: =Model!I122 -> 1 | J29: =Model!J122 -> 0.603 | K29: =Model!K122 -> 0.60603 | L29: =Model!L122 -> 0.6090903 | M29: =Model!M122 -> 0.6121812 | ... O29: =Model!O122 -> 0.61845605
B30: Total Capex | F30: =+SUM(F28:F29) -> 2 | G30: =+SUM(G28:G29) -> 2 | H30: =+SUM(H28:H29) -> 2 | I30: =+SUM(I28:I29) -> 2 | J30: =+SUM(J28:J29) -> 1.206 | K30: =+SUM(K28:K29) -> 1.21206 | L30: =+SUM(L28:L29) -> 1.2181806 | M30: =+SUM(M28:M29) -> 1.2243624 | ... O30: =+SUM(O28:O29) -> 1.2369121
B31: Capex % of Revenue | H31: =+H30/H$7 -> 0.033333333 | I31: =+I30/I$7 -> 0.033333333 | J31: =+J30/J$7 -> 0.02 | K31: =+K30/K$7 -> 0.02 | L31: =+L30/L$7 -> 0.02 | M31: =+M30/M$7 -> 0.02 | N31: =+N30/N$7 -> 0.02 | O31: =+O30/O$7 -> 0.02
B33: Maintenance Capex % of Revenue | H33: =+H28/H$7 -> 0.016666667 | I33: =+I28/I$7 -> 0.016666667 | J33: =+J28/J$7 -> 0.01 | K33: =+K28/K$7 -> 0.01 | L33: =+L28/L$7 -> 0.01 | M33: =+M28/M$7 -> 0.01 | N33: =+N28/N$7 -> 0.01 | O33: =+O28/O$7 -> 0.01
B34: Growth Capex % of Revenue | H34: =+H29/H$7 -> 0.016666667 | I34: =+I29/I$7 -> 0.016666667 | J34: =+J29/J$7 -> 0.01 | K34: =+K29/K$7 -> 0.01 | L34: =+L29/L$7 -> 0.01 | M34: =+M29/M$7 -> 0.01 | N34: =+N29/N$7 -> 0.01 | O34: =+O29/O$7 -> 0.01
B36: Adj. EBITDA - Capex | F36: =+F25-F30 -> -6 | G36: =+G25-G30 -> -6 | H36: =+H25-H30 -> -6 | I36: =+I25-I30 -> -6 | J36: =+J25-J30 -> 37.848 | K36: =+K25-K30 -> 38.09848 | L36: =+L25-L30 -> 38.351465 | M36: =+M25-M30 -> 38.606979 | ... O36: =+O25-O30 -> 39.1257 | Q36: =+IFERROR(((L36/J36)^(1/(2026-2024)))-1,"n/a") -> 0.0066291685 | R36: =+IFERROR(((O36/L36)^(1/(2029-2026)))-1,"n/a") -> 0.0066845125 | S36: =+IFERROR(((O36/J36)^(1/(2029-2024)))-1,"n/a") -> 0.0066623745
